coorddetect/__init__.py
coorddetect/__main__.py
coorddetect/cli.py
coorddetect/core.py
coorddetect-0.1.1.dist-info/licenses/LICENSE
coorddetect-0.1.1.dist-info/METADATA
coorddetect-0.1.1.dist-info/WHEEL
coorddetect-0.1.1.dist-info/entry_points.txt
coorddetect-0.1.1.dist-info/top_level.txt
coorddetect-0.1.1.dist-info/RECORD
