Metadata-Version: 2.4
Name: coorddetect
Version: 0.1.1
Summary: Automatic XYZ coordinate detection and spatial diagnostics for messy tabular data
Author-email: Kenneth Kwabena Kenney <kenneykennethkwabena@gmail.com>
License: MIT
Project-URL: Homepage, https://github.com/KennethKwabenaKenney/coorddetect
Project-URL: Issues, https://github.com/KennethKwabenaKenney/coorddetect/issues
Keywords: XYZ,coordinates,geomatics,lidar,surveying,point-cloud,GIS
Requires-Python: >=3.9
License-File: LICENSE
Requires-Dist: numpy
Requires-Dist: pandas
Requires-Dist: scipy
Dynamic: license-file
